agentgog/__init__.py
agentgog/ai_classifier.py
agentgog/ai_classifier.py.older
agentgog/calendar_extractor.py
agentgog/check_openrouter_prices.py
agentgog/cli.py
agentgog/memo_extractor.py
agentgog/ollama_client.py
agentgog/one_agent.py
agentgog/one_agent.py.newer
agentgog/openrouter_client.py
agentgog/provider.py
agentgog/smol_codeagent.py
agentgog/smol_common.py
agentgog/smol_qrpayment.py
agentgog/smol_translator.py
agentgog/task_extractor.py
agentgog/test_free_models.py
agentgog/test_ollama.py
agentgog-0.1.7.dist-info/METADATA
agentgog-0.1.7.dist-info/WHEEL
agentgog-0.1.7.dist-info/entry_points.txt
agentgog-0.1.7.dist-info/RECORD
