Metadata-Version: 2.4
Name: agentgog
Version: 0.1.7
Summary: Add your description here
Author-email: coder <jaromrax@gmail.com>
Requires-Python: >=3.12
Requires-Dist: click
Requires-Dist: console
Requires-Dist: google-api-python-client
Requires-Dist: google-auth-httplib2
Requires-Dist: google-auth-oauthlib
Requires-Dist: litellm>=1.81.3
Requires-Dist: matplotlib>=3.10.8
Requires-Dist: numpy>=2.4.1
Requires-Dist: pandas>=3.0.0
Requires-Dist: prompt-toolkit
Requires-Dist: qrcode>=8.2
Requires-Dist: requests
Requires-Dist: simplenote>=2.1.4
Requires-Dist: smolagents[openai]>=1.24.0
Requires-Dist: sympy>=1.14.0
